.gitignore
CHANGELOG
MANIFEST.in
README.rst
googlemusicplayer_screenshot.png
setup.py
bin/googlemusic
googlemusicplayer.egg-info/PKG-INFO
googlemusicplayer.egg-info/SOURCES.txt
googlemusicplayer.egg-info/dependency_links.txt
googlemusicplayer.egg-info/requires.txt
googlemusicplayer.egg-info/top_level.txt
music_player/__init__.py
music_player/lastfm.py
music_player/music_player.py
music_player/ui.py
music_player/widget.py