Metadata-Version: 1.0
Name: googlemusicplayer
Version: 0.6
Summary: a GTK music player using google music API
Home-page: UNKNOWN
Author: Yohann Gabory
Author-email: yohann@gabory.fr
License: UNKNOWN
Platform: UNKNOWN
